{"username":"weneebeauty","authorid":"5894202","url":"http:\/\/weneebeauty.pixnet.net\/blog\/post\/740","title":"《 Wenée 薇妮體雕 顧客心得體驗文》","content":"<span style=\"font-size: 18px;\"><span style=\"font-family:Arial;\"><\/span>我的工作是金融業的行員，大部份的時間都是坐著，下午常<wbr>常會有客戶帶東西來請我們吃，有時也會有慶生會，所以下<wbr>半身後來就慢慢不像學生時期那麼的標準。 我跟大部份的女生一樣都不滿意自已的下半身，後來，有一<wbr>次跟妹妹去逛百貨公司知道了薇妮體雕的專櫃，因為專櫃小<wbr>姐嘉文跟我們介紹的很仔細，本來只是妹妹想要先訂購，但<wbr>我在一旁也聽的很認真當下也提出很多問題，嘉文都很有耐<wbr>心的一一說明，讓我覺得雖然不是我要買，但她依然態度親<wbr>切，讓我感覺很好，所以也決定要對自已好一點，買這個來<wbr>讓自已身材變的更好。\n<p>\n<\/p><br>後來就跟妹妹一起訂了，我只要上班跟參加朋友的聚會我都<wbr>會穿塑身衣看起來體態好很多視覺上少了五公斤，因為穿了<wbr>一陣子的塑身衣，身材真的變的比之前好了，感謝薇妮體雕<wbr>做出這麼優質的塑身衣，還有超棒的售後服務，未來有機會<wbr>我一定會介紹我想要變美的朋友，因為我們一家都是妳們的<wbr>見證者，之後有活動，也別忘了跟我們聯絡，有時間我們一<wbr>定會參加的，謝謝妳們的用心!<\/span><span style=\"font-size: 18px;\">\n<p><br>\n<\/p>\n<p><img src=\"https:\/\/pic.pimg.tw\/weneebeauty\/1447315243-482872027.jpg?v=1447315298\" alt=\"390701_10151484995212600_1306813532_n.jpg\">&nbsp;\n<\/p><\/span>","blog-name":"WENĒE薇妮體雕","blog-id":"5894202","blog-category":"13","date":"2015-11-12","hits":"28"}
{"username":"tiffany41149","authorid":"5894300","url":"http:\/\/tiffany41149.pixnet.net\/blog\/post\/1067-%5bl%26t%5d-%e5%a4%a7%e6%8e%a8%e7%b6%bf%e8%b0%b7%e7%b5%90%e5%a9%9a%e5%bc%8f%28%e5%8f%b0%e4%b8%ad%29%e6%af%9b%e7%89%87%e5%88%86%e4%ba%ab.%e6%94%9d%e5%bd%b1%e5%b8%ab%2b","title":"♔ⓁⓉ♕ 大推綿谷結婚式(台中)毛片分享.攝影師+化妝師+燈光師 3師合1 毛片幾乎就是成品了耶~是要修哪裡?(圖多)","content":"<p>9月拍照的毛片出爐了\n<\/p>\n<p>這次幫我們拍攝的成員\n<\/p>\n<p>我沒有指定因為我相信他們都有辦法拍出我要的東西\n<\/p>\n<p>攝影師:小薛<img src=\"http:\/\/verywed.com\/forum\/images\/bagel\/cool-bagel.png\" alt=\"\">\n<\/p>\n<p>燈光師:阿志<img src=\"http:\/\/verywed.com\/forum\/images\/bagel\/ya-bagel.png\" alt=\"\">\n<\/p>\n<p>造型師:菲比<img src=\"http:\/\/verywed.com\/forum\/images\/bagel\/love-bagel.png\" alt=\"\">\n<\/p>\n<p>事前作好功課給他們拍起來一路都很順\n<\/p>\n<p>只是我臨時加了一個地點到我家去拍<img src=\"http:\/\/verywed.com\/forum\/images\/vera\/jump-vera.png\" alt=\"\">\n<\/p>\n<p>瞬間變的時間很緊湊\n<\/p>\n<p>不過還是順利拍攝完成\n<\/p>\n<p>菲比也很專業的幫我換了好幾個造型\n<\/p>\n<p>因為我喜歡自然的感覺加上我頭髮很長所以整個都是利用我的真髮\n<\/p>\n<p>阿志打光也是超級棒的\n<\/p>\n<p>我們在暗暗的地方拍黑婚紗卻看起來像是白天一樣\n<\/p>\n<p>那天騎時拍照後面都有點陰天了\n<\/p>\n<p>但是光打的好人生就是彩色的\n<\/p>\n<p><img src=\"http:\/\/verywed.com\/forum\/images\/watermelon-ma\/emo1-7.png\" alt=\"\">\n<\/p>\n<p>攝影師小薛更是認真嚴就我的參考圖近量把我想要的畫面都表現出來\n<\/p>\n<p>出來的成品完全超乎我想像\n<\/p>\n<p>想說在那種燈光不足的天氣還可以拍的這麼棒\n<\/p>\n<p>我有自己做道具也有租道具\n<\/p>\n<p>但因為我禮服風格很鮮明所以其實基本上都要靠我自己的肢體去撐這幾件禮服\n<\/p>\n<p>同場加應掏寶買的寶藍色晚禮服\n<\/p>\n<p>那一系列我超愛的<img src=\"http:\/\/verywed.com\/forum\/images\/vera\/shy-vera.png\" alt=\"\">\n<\/p>\n<p>簡單的裝髮不佩任何飾品\n<\/p>\n<p>讓我想把她放大來當無框畫\n<\/p>\n<p>選了一個比較少人知道的婚紗基地\n<\/p>\n<p>因為太多人透明教堂都長一樣我偏偏不喜歡那種三角型\n<\/p>\n<p>一樣在苗栗但是三義離台中又更近了\n<\/p>\n<p>讓老公不用舟車勞頓的<img src=\"http:\/\/verywed.com\/forum\/images\/wade\/marry-wade.png\" alt=\"\">\n<\/p>\n<p><img src=\"http:\/\/s.verywed.com\/1200-1200\/s1\/2015\/10\/06\/1444130346_592499831d0df740eb84105e59bf0514.jpg\" alt=\"\"><br><br><img src=\"http:\/\/s.verywed.com\/1200-1200\/s1\/2015\/10\/06\/1444130346_4681a671df91fdf65028b177c6e40133.jpg\" alt=\"\">\n<\/p>\n<p><br><img src=\"http:\/\/s.verywed.com\/1200-1200\/s1\/2015\/10\/06\/1444130637_90a9ba628c5537ed1ce33c7752e6105b.jpg\" alt=\"\"><br><br><br><br><br><img src=\"http:\/\/s.verywed.com\/1200-1200\/s1\/2015\/10\/06\/1444130346_6f8cf57ca48625d769a776439e5b5ced.jpg\" alt=\"\"><br><img src=\"http:\/\/s.verywed.com\/1200-1200\/s1\/2015\/10\/06\/1444130656_3c929b73a2747f11e03ba24510b1e8c7.jpg\" alt=\"\"><br><br><br><img src=\"http:\/\/s.verywed.com\/1200-1200\/s1\/2015\/10\/06\/1444130346_a24d5a6e7fde7e9bbc1fc61b3ba59adb.jpg\" alt=\"\"><br><br><img src=\"http:\/\/s.verywed.com\/1200-1200\/s1\/2015\/10\/06\/1444130346_3fc72c5a288aaff5257edb5822bddea6.jpg\" alt=\"\"><br><br><img src=\"http:\/\/s.verywed.com\/1200-1200\/s1\/2015\/10\/06\/1444130346_57f4d575f7912c1842cd166c83f45059.jpg\" alt=\"\"><br><br><img src=\"http:\/\/s.verywed.com\/1200-1200\/s1\/2015\/10\/06\/1444130346_92cc9801e2796dc4c0e957b4d5a0106b.jpg\" alt=\"\"><br><br><br><br><img src=\"http:\/\/s.verywed.com\/1200-1200\/s1\/2015\/10\/06\/1444130346_fc4b0592edc29bc47f703dcc6b4a6c86.jpg\" alt=\"\"><br><img src=\"http:\/\/s.verywed.com\/1200-1200\/s1\/2015\/10\/06\/1444130366_1f39719949aa743687a608b4591b21d4.jpg\" alt=\"\"><br><br><img src=\"http:\/\/s.verywed.com\/1200-1200\/s1\/2015\/10\/06\/1444130366_0aa8ea714691c9219057b1c77eeed1fc.jpg\" alt=\"\"><br><br><img src=\"http:\/\/s.verywed.com\/1200-1200\/s1\/2015\/10\/06\/1444130366_f4bc10c2d1e88ca457d04be4c45a942e.jpg\" alt=\"\"><br><br><img src=\"http:\/\/s.verywed.com\/1200-1200\/s1\/2015\/10\/06\/1444130366_b5835121729629c0aed99ef69d73ca52.jpg\" alt=\"\"><br><br><img src=\"http:\/\/s.verywed.com\/1200-1200\/s1\/2015\/10\/06\/1444130366_51781c7b30c98b1535171aed55adc595.jpg\" alt=\"\"><br><br><img src=\"http:\/\/s.verywed.com\/1200-1200\/s1\/2015\/10\/06\/1444130366_c591940f59aab54285b857c69bfe9b5d.jpg\" alt=\"\"><br><br><img src=\"http:\/\/s.verywed.com\/1200-1200\/s1\/2015\/10\/06\/1444130366_a86250d7ac7cfcd8c1009a00ba07ebd1.jpg\" alt=\"\"><br><br><img src=\"http:\/\/s.verywed.com\/1200-1200\/s1\/2015\/10\/06\/1444130366_65f165e3a65e5a1aba6246c5da98dcdf.jpg\" alt=\"\"><br><br>\n<\/p>\n<p>有喜歡的朋友可以幫我推推\n<\/p>\n<p>有任何想知道的資訊也可以問我喔~~\n<\/p>\n<p><img src=\"http:\/\/verywed.com\/forum\/images\/watermelon-ma\/emo1-4.png\" alt=\"\">\n<\/p>","blog-name":"**踢昏你-簡**小生活大確性~~","blog-id":"5894300","blog-category":"13","date":"2015-11-12","hits":"45"}
{"username":"dear1143456","authorid":"5895288","url":"http:\/\/dear1143456.pixnet.net\/blog\/post\/294986","title":"要如何讓自己變的有女人味 ?","content":"<p>本身我就很嬌小了,快20歲了卻覺得自己沒有品味\n<\/p>\n<p>覺得有些女孩可以打扮那麽好,為何只有我不可以 ?\n<\/p>\n<p>這個問題其實在我心裡面很久了\n<\/p>\n<p>卻想不出所以然&nbsp; 好困擾&nbsp;&nbsp;\n<\/p>\n<p>有人可以推推好看的衣服或文章讓我參考嗎 ?\n<\/p>","blog-name":"dear1143456的部落格","blog-id":"5895288","blog-category":"0","date":"2015-11-13","hits":"8"}
{"username":"myway2015","authorid":"5895511","url":"http:\/\/myway2015.pixnet.net\/blog\/post\/297719","title":"手創包","content":"<p><strong><span style=\"font-family: 新細明體;\"><span style=\"font-size: 20px;\">側背口巾包,簡易又時尚,攜帶小物很方便<\/span><\/span><\/strong><br>\n<\/p>\n<p><img src=\"https:\/\/pic.pimg.tw\/myway2015\/1447398102-1245290968_n.jpg?v=1447398182\" alt=\"側背小口巾包2\">&nbsp;\n<\/p>\n<p><img src=\"https:\/\/pic.pimg.tw\/myway2015\/1447398102-4098602823_n.jpg?v=1447398182\" alt=\"側背小口巾包1\">&nbsp;\n<\/p>","blog-name":"MyWay手創包的部落格","blog-id":"5895511","blog-category":"28","date":"2015-11-13","hits":"28"}
{"username":"mimimi781012","authorid":"5895203","url":"http:\/\/mimimi781012.pixnet.net\/blog\/post\/298070-%e3%80%90%e6%96%b0%e7%ab%b9%e6%bc%be%e9%ab%ae%e8%97%9d%e9%80%a0%e5%9e%8bhair-salon%e3%80%91-%e5%85%89%e6%a3%8d%e7%af%80%e7%87%99%e6%9f%93%e7%be%8e%e9%ba%97","title":"【新竹漾髮藝造型Hair Salon】-光棍節燙染美麗髮型日記","content":"<p><span style=\"font-family: 新細明體, serif;\"><img title=\"40644\" src=\"https:\/\/pic.pimg.tw\/mimimi781012\/1447399590-1379434386_n.jpg?v=1447399591\" alt=\"40644\" width=\"218\" height=\"319\" border=\"0\" \/> &nbsp;<img title=\"40656\" src=\"https:\/\/pic.pimg.tw\/mimimi781012\/1447399847-2335297_n.jpg\" alt=\"40656\" width=\"224\" height=\"325\" border=\"0\" \/> &nbsp;&nbsp;&nbsp;<\/span><\/p>\r\n<p><span style=\"font-size: 12pt;\"><span style=\"font-family: 新細明體, serif;\">嘿嘿<\/span>!!<span style=\"font-family: 新細明體, serif;\">今年的<\/span>11.11<span style=\"font-family: 新細明體, serif;\">光棍節依然還是我的節日囉<\/span>!<\/span><\/p>\r\n<p><span style=\"font-size: 12pt;\"><span style=\"font-family: 新細明體, serif;\">不過店長人真的很好<\/span><span style=\"font-family: 新細明體, serif;\">，還讓我今天排休呢!<\/span><\/span><\/p>\r\n<p><span style=\"font-family: 新細明體, serif; font-size: 12pt;\">所以早上享受完一個人的早餐，就逛了網購血拼<\/span><\/p>\r\n<p><span style=\"font-size: 12pt;\"><span style=\"font-family: 新細明體, serif;\">中午就到新竹漾髮藝造型Hair Salon<\/span><span style=\"font-family: 新細明體, serif;\">用頭髮囉<\/span><span style=\"font-family: Arial, sans-serif;\" lang=\"EN-US\">!<\/span><\/span><\/p>\r\n<p><span style=\"font-size: 12pt;\"><span style=\"font-family: 新細明體, serif;\">已經好一陣子都沒有去找設計師<\/span>Demi<span style=\"font-family: 新細明體, serif;\">用頭髮了<\/span><\/span><\/p>\r\n<p><span style=\"font-size: 12pt;\"><span style=\"font-family: 新細明體, serif;\">整個髮型就給它荒廢在那裡<\/span>XD<\/span><\/p>\r\n<p><span style=\"font-size: 12pt;\"><span style=\"font-family: 新細明體, serif;\">由於晚上跟好姐妹約了一起去吃大餐<\/span>Happly<span style=\"font-family: 新細明體, serif;\">一下<\/span><\/span><\/p>\r\n<p><span style=\"font-family: 新細明體, serif; font-size: 12pt;\">這次我們的主題還是童話故事的女主角<\/span><\/p>\r\n<p><span style=\"font-size: 12pt;\"><span style=\"font-family: 新細明體, serif;\">嘿嘿<\/span>!<span style=\"font-family: 新細明體, serif;\">我的角色還是愛麗絲呢<\/span>~~~<\/span><\/p>\r\n<p><span style=\"font-size: 12pt;\"><img title=\"40645\" src=\"https:\/\/pic.pimg.tw\/mimimi781012\/1447399880-2418853059_n.jpg?v=1447399881\" alt=\"40645\" width=\"285\" height=\"389\" border=\"0\" \/> &nbsp;<\/span><\/p>\r\n<p><span style=\"font-size: 12pt; background-color: #ffff00;\"><span style=\"font-family: 新細明體, serif;\">這次跟漾髮藝造型Hair Salon<\/span><em><span style=\"font-family: 新細明體, serif; font-style: normal;\">設計師<\/span><\/em>Demi<span style=\"font-family: 新細明體, serif;\">討論髮型後<\/span><\/span><\/p>\r\n<p><span style=\"font-family: 新細明體, serif; font-size: 12pt; background-color: #ffff00;\">決定要用一個橘紅和紫色的漸層搭配<\/span><\/p>\r\n<p><span style=\"font-family: 新細明體, serif; font-size: 12pt; background-color: #ffff00;\">因為皮膚不是很白皙的我<\/span><\/p>\r\n<p><span style=\"font-family: 新細明體, serif; font-size: 12pt; background-color: #ffff00;\">設計師說幫我染這樣的漸層色會讓皮膚比較顯白<\/span><\/p>\r\n<p><span style=\"font-family: 新細明體, serif; font-size: 12pt;\">因為從以前到現在就長期染髮<\/span><\/p>\r\n<p><span style=\"font-family: 新細明體, serif; font-size: 12pt;\">所以顏色也比較難漂掉<\/span><\/p>\r\n<p><span style=\"font-size: 12pt; color: #ff0000;\"><span style=\"font-family: 新細明體, serif;\">不過<\/span>Demi<span style=\"font-family: 新細明體, serif;\">設計師總是都很有耐心細心的幫我處理<\/span><\/span><\/p>\r\n<p><span style=\"font-size: 12pt; color: #ff0000;\"><span style=\"font-family: 新細明體, serif;\">這金色真的太值得留念啦<\/span>!!<\/span><\/p>\r\n<p><span style=\"font-size: 12pt; color: #ff0000;\"><span style=\"font-family: 新細明體, serif;\">不過漾髮藝造型<\/span><em><span style=\"font-family: 新細明體, serif; font-style: normal;\">除了技術不錯<\/span><\/em><\/span><\/p>\r\n<p><span style=\"font-size: 12pt; color: #ff0000;\"><em><span style=\"font-family: 新細明體, serif; font-style: normal;\">店裡給客人用的染燙劑品質也很好<img src=\"\/\/s.pixfs.net\/f.pixnet.net\/images\/emotions\/017.gif\" alt=\"\" border=\"0\" \/><img src=\"\/\/s.pixfs.net\/f.pixnet.net\/images\/emotions\/017.gif\" alt=\"\" border=\"0\" \/><\/span><\/em><\/span><\/p>\r\n<p><span style=\"font-size: 12pt; color: #ff0000;\"><em><span style=\"font-family: 新細明體, serif; font-style: normal;\">所以頭髮都不會隨便就毛躁或用壞<img src=\"\/\/s.pixfs.net\/f.pixnet.net\/images\/emotions\/012.gif\" alt=\"\" border=\"0\" \/><\/span><\/em><\/span><\/p>\r\n<p><span style=\"font-size: 12pt;\">&nbsp;<img title=\"40646\" src=\"https:\/\/pic.pimg.tw\/mimimi781012\/1447399640-1231362312_n.jpg\" alt=\"40646\" width=\"309\" height=\"421\" border=\"0\" \/> &nbsp;<\/span><\/p>\r\n<p><span style=\"font-size: 12pt;\">&nbsp;<img title=\"40648\" src=\"https:\/\/pic.pimg.tw\/mimimi781012\/1447399653-2603374568_n.jpg\" alt=\"40648\" width=\"199\" height=\"271\" border=\"0\" \/> &nbsp;<img title=\"40649\" src=\"https:\/\/pic.pimg.tw\/mimimi781012\/1447399664-4400150_n.jpg\" alt=\"40649\" width=\"203\" height=\"277\" border=\"0\" \/> &nbsp;<\/span><\/p>\r\n<p><span style=\"font-family: 新細明體, serif; font-size: 12pt;\">因為前陣子工作太忙都沒時間整理<\/span><\/p>\r\n<p><span style=\"font-size: 12pt;\"><span style=\"font-family: 新細明體, serif;\">跟<\/span>Nancy<span style=\"font-family: 新細明體, serif;\">髮型助理也邊用頭髮一直邊聊天<\/span><\/span><\/p>\r\n<p><span style=\"font-size: 12pt;\"><span style=\"font-family: 新細明體, serif;\">一直說我怎麼還單身呢<\/span>!! <\/span><\/p>\r\n<p><span style=\"font-size: 12pt;\"><span style=\"font-family: 新細明體, serif;\">沒辦法好男人都不知去哪啦<\/span>~~~<img src=\"\/\/s.pixfs.net\/f.pixnet.net\/images\/emotions\/007.gif\" alt=\"\" border=\"0\" \/><img src=\"\/\/s.pixfs.net\/f.pixnet.net\/images\/emotions\/007.gif\" alt=\"\" border=\"0\" \/><\/span><\/p>\r\n<p><span style=\"font-size: 12pt;\"><span style=\"font-family: 新細明體, serif;\">反正目前都先這樣囉<\/span>! <span style=\"font-family: 新細明體, serif;\">單身也是很不錯嘛!<img src=\"\/\/s.pixfs.net\/f.pixnet.net\/images\/emotions\/009.gif\" alt=\"\" border=\"0\" \/><\/span><br \/><\/span><\/p>\r\n<p><span style=\"font-size: 12pt;\">&nbsp;<img title=\"40651\" src=\"https:\/\/pic.pimg.tw\/mimimi781012\/1447399698-2775923999_n.jpg?v=1447399700\" alt=\"40651\" width=\"196\" height=\"268\" border=\"0\" \/> &nbsp;<img title=\"40660\" src=\"https:\/\/pic.pimg.tw\/mimimi781012\/1447399721-348080440_n.jpg\" alt=\"40660\" width=\"200\" height=\"268\" border=\"0\" \/> &nbsp;<\/span><\/p>\r\n<p><span style=\"font-size: 12pt;\"><span style=\"font-family: 新細明體, serif;\">把自己用的美美的<\/span><span style=\"font-family: 新細明體, serif;\">，開開心心就好囉!<\/span><\/span><\/p>\r\n<p><span style=\"font-family: 新細明體, serif; font-size: 12pt;\">因為這次除了染髮也加上燙髮<\/span><\/p>\r\n<p><span style=\"font-family: 新細明體, serif; font-size: 12pt;\">最後店長也幫我親自上了彩妝<\/span><\/p>\r\n<p><span style=\"font-family: 新細明體, serif; font-size: 12pt; color: #ff6600;\">真的很喜歡店長幫我化的妝，自然氣色好<\/span><\/p>\r\n<p><span style=\"font-size: 12pt;\"><span style=\"font-family: 新細明體, serif;\">會來漾髮藝造型Hair Salon<\/span><\/span><\/p>\r\n<p><span style=\"font-family: 新細明體, serif; font-size: 12pt;\">也是因為之前喝表姐喜酒<\/span><\/p>\r\n<p><span style=\"font-family: 新細明體, serif; font-size: 12pt;\">因為要用髮妝的關係<\/span><\/p>\r\n<p><span style=\"font-family: 新細明體, serif; font-size: 12pt; color: #ff0000;\">在網路上看到有網友推薦<\/span><\/p>\r\n<p><span style=\"font-size: 12pt; color: #ff0000;\"><span style=\"font-family: 新細明體, serif;\">這間新竹漾髮藝造型Hair Salon<\/span><em><span style=\"font-family: 新細明體, serif; font-style: normal;\">彩妝技術很讚<\/span><\/em><\/span><\/p>\r\n<p><span style=\"font-family: 新細明體, serif; font-size: 12pt; color: #ff0000;\">當時彩妝師幫我和老媽化完妝<\/span><\/p>\r\n<p><span style=\"font-family: 新細明體, serif; font-size: 12pt; color: #ff0000;\">都很喜歡這樣的妝感<\/span><\/p>\r\n<p><span style=\"font-family: 新細明體, serif; font-size: 12pt; color: #ff0000;\">而且店裡的氛圍很放鬆、乾淨<\/span><\/p>\r\n<p><span style=\"font-family: 新細明體, serif; font-size: 12pt; color: #ff0000;\">設計師、髮型助理都很親切招呼我們<img src=\"\/\/s.pixfs.net\/f.pixnet.net\/images\/emotions\/fox_12.gif\" alt=\"\" border=\"0\" \/><\/span><\/p>\r\n<p><span style=\"font-size: 12pt;\"><span style=\"font-family: 新細明體, serif;\">後來就開始來漾髮藝造型Hair Salon<\/span><span style=\"font-family: 新細明體, serif;\">用頭髮囉!<\/span><\/span><\/p>\r\n<p><span style=\"font-size: 12pt;\">&nbsp;<img title=\"40653\" src=\"https:\/\/pic.pimg.tw\/mimimi781012\/1447399754-2906987167_n.jpg\" alt=\"40653\" width=\"209\" height=\"280\" border=\"0\" \/> &nbsp;<img title=\"40655\" src=\"https:\/\/pic.pimg.tw\/mimimi781012\/1447399766-2449060566_n.jpg\" alt=\"40655\" width=\"205\" height=\"278\" border=\"0\" \/> &nbsp;<\/span><\/p>\r\n<p><span style=\"font-family: 新細明體, serif; font-size: 12pt;\">這次髮型也算是久違的大改造<\/span><\/p>\r\n<p><span style=\"font-family: 新細明體, serif; font-size: 12pt;\">不過看起來真的好有女人味啊!<\/span><\/p>\r\n<p><span style=\"font-family: 新細明體, serif; font-size: 12pt;\">跟原本剛進來髮廊拍的樣子完全不一樣啊!<\/span><\/p>\r\n<p><span style=\"font-family: 新細明體, serif; font-size: 12pt;\">我之前怎麼可以這麼邋遢啦&hellip;<\/span><\/p>\r\n<p><span style=\"font-family: 新細明體, serif; font-size: 12pt;\">這次因為搭配我的童話故事主題趴<\/span><\/p>\r\n<p><span style=\"font-family: 新細明體, serif; font-size: 12pt;\">設計師還幫我用個辮子，看起來好俏皮可愛呢!<\/span><\/p>\r\n<p><span style=\"font-size: 12pt;\">Nancy<span style=\"font-family: 新細明體, serif;\">還開玩笑的說<\/span>~~&nbsp; <span style=\"font-family: 新細明體, serif;\">等等出去一定一票人要電話啦<\/span>XD<img src=\"\/\/s.pixfs.net\/f.pixnet.net\/images\/emotions\/fox_13.gif\" alt=\"\" border=\"0\" \/><\/span><\/p>\r\n<p><span style=\"font-size: 12pt;\"><span style=\"font-family: 新細明體, serif;\">不過我想今天還是美美的當愛麗絲跟姐妹過光棍節吧<\/span>!<img src=\"\/\/s.pixfs.net\/f.pixnet.net\/images\/emotions\/fox_10.gif\" alt=\"\" border=\"0\" \/><\/span><\/p>\r\n<p><span style=\"font-size: 12pt;\">&nbsp;<img title=\"40658\" src=\"https:\/\/pic.pimg.tw\/mimimi781012\/1447399796-3272425086_n.jpg?v=1447399798\" alt=\"40658\" width=\"288\" height=\"385\" border=\"0\" \/> &nbsp;&nbsp;&nbsp;<\/span><\/p>\r\n<p><span style=\"font-family: 新細明體, serif; font-size: 12pt;\" lang=\"EN-US\">&nbsp;<\/span><\/p>","blog-name":"ﾟ･*:✱雨蕙✱ .｡.:*･ﾟ","blog-id":"5895203","blog-category":"28","date":"2015-11-12","hits":"18"}
{"username":"a7770392","authorid":"5895957","url":"http:\/\/a7770392.pixnet.net\/blog\/post\/873557-eunice%e6%96%b0%e5%a8%98%e7%a7%98%e6%9b%b8%e6%9c%8d%e5%8b%99%e9%a0%85%e7%9b%ae","title":"Eunice新娘秘書服務項目","content":"<ul>\n\t<div>\n\t\t<div style=\"margin-left: 20px;\"><em><strong><span style=\"font-family: 新細明體;\"><span style=\"background-color: rgb(255, 255, 255);\"><span style=\"color: rgb(0, 0, 255);\"><span style=\"font-size: 16px;\"><span style=\"font-family: 'Times New Roman';\"><\/span>服務內容：<\/span><\/span><\/span><\/span><\/strong><\/em>\n\t\t<\/div>\n\t\t<div><span style=\"font-family: 新細明體;\"><span style=\"background-color: rgb(255, 255, 255);\"><span style=\"color: rgb(0, 0, 255);\"><span style=\"font-size: 16px;\"><br><\/span><\/span><\/span><\/span>\n\t\t<\/div>\n\t\t<div style=\"margin-left: 20px;\"><em><strong><span style=\"font-family: 新細明體;\"><span style=\"background-color: rgb(255, 255, 255);\"><span style=\"color: rgb(0, 0, 255);\"><span style=\"font-size: 16px;\">新娘單一個妝髮$5000<\/span><\/span><\/span><\/span><\/strong><\/em>\n\t\t<\/div>\n\t\t<div><span style=\"font-family: 新細明體;\"><span style=\"background-color: rgb(255, 255, 255);\"><span style=\"color: rgb(0, 0, 255);\"><span style=\"font-size: 16px;\"><span style=\"font-family: 新細明體;\"><\/span><br><\/span><\/span><\/span><\/span>\n\t\t<\/div>\n\t\t<div><em><strong><span style=\"font-family: 新細明體;\"><span style=\"background-color: rgb(255, 255, 255);\"><span style=\"color: rgb(0, 0, 255);\"><span style=\"font-size: 16px;\">午宴$15000（三套禮服，包含迎娶白紗，贈媽媽妝髮和新郎妝髮，安瓶*1）<\/span><\/span><\/span><\/span><\/strong><\/em>\n\t\t<\/div>\n\t\t<div><span style=\"font-family: 新細明體;\"><span style=\"background-color: rgb(255, 255, 255);\"><span style=\"color: rgb(0, 0, 255);\"><span style=\"font-size: 16px;\"><br><\/span><\/span><\/span><\/span>\n\t\t<\/div>\n\t\t<div><em><strong><span style=\"font-family: 新細明體;\"><span style=\"background-color: rgb(255, 255, 255);\"><span style=\"color: rgb(0, 0, 255);\"><span style=\"font-size: 16px;\">晚宴$15000（三套禮服，包含迎娶白紗，贈媽媽妝髮和新郎妝髮，安瓶*1）<\/span><\/span><\/span><\/span><\/strong><\/em>\n\t\t<\/div>\n\t\t<div><span style=\"font-family: 新細明體;\"><span style=\"background-color: rgb(255, 255, 255);\"><span style=\"color: rgb(0, 0, 255);\"><span style=\"font-size: 16px;\"><br><\/span><\/span><\/span><\/span>\n\t\t<\/div>\n\t\t<div><em><strong><span style=\"font-family: 新細明體;\"><span style=\"background-color: rgb(255, 255, 255);\"><span style=\"color: rgb(0, 0, 255);\"><span style=\"font-size: 16px;\">補請\/歸寧$15000（三套禮服，贈媽媽妝髮和新郎妝髮，安瓶*1）<\/span><\/span><\/span><\/span><\/strong><\/em>\n\t\t<\/div>\n\t\t<div><span style=\"font-family: 新細明體;\"><span style=\"background-color: rgb(255, 255, 255);\"><span style=\"color: rgb(0, 0, 255);\"><span style=\"font-size: 16px;\"><br><\/span><\/span><\/span><\/span>\n\t\t<\/div>\n\t\t<div><em><strong><span style=\"font-family: 新細明體;\"><span style=\"background-color: rgb(255, 255, 255);\"><span style=\"color: rgb(0, 0, 255);\"><span style=\"font-size: 16px;\">補請\/歸寧$12000（兩套禮服，贈媽媽妝髮和新郎妝髮，安瓶*1）<\/span><\/span><\/span><\/span><\/strong><\/em>\n\t\t<\/div>\n\t\t<div><span style=\"font-family: 新細明體;\"><span style=\"background-color: rgb(255, 255, 255);\"><span style=\"color: rgb(0, 0, 255);\"><span style=\"font-size: 16px;\"><br><\/span><\/span><\/span><\/span>\n\t\t<\/div>\n\t\t<div><em><strong><span style=\"font-family: 新細明體;\"><span style=\"background-color: rgb(255, 255, 255);\"><span style=\"color: rgb(0, 0, 255);\"><span style=\"font-size: 16px;\">伴娘、婆婆、親友妝髮，一位$1200<\/span><\/span><\/span><\/span><\/strong><\/em>\n\t\t<\/div>\n\t\t<div><span style=\"font-family: 新細明體;\"><span style=\"background-color: rgb(255, 255, 255);\"><span style=\"color: rgb(0, 0, 255);\"><span style=\"font-size: 16px;\"><br><\/span><\/span><\/span><\/span>\n\t\t<\/div>\n\t\t<div><em><strong><span style=\"font-family: 新細明體;\"><span style=\"background-color: rgb(255, 255, 255);\"><span style=\"color: rgb(0, 0, 255);\"><span style=\"font-size: 16px;\">南部以北，需酌收車馬費 中部$1500，北部$3000<\/span><\/span><\/span><\/span><\/strong><\/em>\n\t\t<\/div>\n\t\t<div><span style=\"font-family: 新細明體;\"><span style=\"background-color: rgb(255, 255, 255);\"><span style=\"color: rgb(0, 0, 255);\"><span style=\"font-size: 16px;\"><br><\/span><\/span><\/span><\/span>\n\t\t<\/div>\n\t\t<div><em><strong><span style=\"font-family: 新細明體;\"><span style=\"background-color: rgb(255, 255, 255);\"><span style=\"color: rgb(0, 0, 255);\"><span style=\"font-size: 16px;\">‧早妝到府服務<\/span><\/span><\/span><\/span><\/strong><\/em>\n\t\t<\/div>\n\t\t<div><em><strong><span style=\"font-family: 新細明體;\"><span style=\"background-color: rgb(255, 255, 255);\"><span style=\"color: rgb(0, 0, 255);\"><span style=\"font-size: 16px;\">&nbsp; &nbsp; &nbsp; &nbsp; &nbsp; &nbsp; &nbsp; &nbsp; &nbsp; &nbsp;<\/span><\/span><\/span><\/span><\/strong><\/em>\n\t\t<\/div>\n\t\t<div><em><strong><span style=\"font-family: 新細明體;\"><span style=\"background-color: rgb(255, 255, 255);\"><span style=\"color: rgb(0, 0, 255);\"><span style=\"font-size: 16px;\">‧或宴客前約2.5小時至飯店\/餐廳化妝,隨後即宴客.&nbsp;<\/span><\/span><\/span><\/span><\/strong><\/em>\n\t\t<\/div>\n\t\t<div><em><strong><span style=\"font-family: 新細明體;\"><span style=\"background-color: rgb(255, 255, 255);\"><span style=\"color: rgb(0, 0, 255);\"><span style=\"font-size: 16px;\">&nbsp; &nbsp; &nbsp; &nbsp; &nbsp; &nbsp; &nbsp; &nbsp; &nbsp; &nbsp; &nbsp;<\/span><\/span><\/span><\/span><\/strong><\/em>\n\t\t<\/div>\n\t\t<div><em><strong><span style=\"font-family: 新細明體;\"><span style=\"background-color: rgb(255, 255, 255);\"><span style=\"color: rgb(0, 0, 255);\"><span style=\"font-size: 16px;\">‧提供假髮、頭飾配件3組<\/span><\/span><\/span><\/span><\/strong><\/em>\n\t\t<\/div>\n\t\t<div><em><strong><span style=\"font-family: 新細明體;\"><span style=\"background-color: rgb(255, 255, 255);\"><span style=\"color: rgb(0, 0, 255);\"><span style=\"font-size: 16px;\">&nbsp; &nbsp; &nbsp; &nbsp; &nbsp; &nbsp; &nbsp; &nbsp; &nbsp;&nbsp;<\/span><\/span><\/span><\/span><\/strong><\/em>\n\t\t<\/div>\n\t\t<div><em><strong><span style=\"font-family: 新細明體;\"><span style=\"background-color: rgb(255, 255, 255);\"><span style=\"color: rgb(0, 0, 255);\"><span style=\"font-size: 16px;\">‧整體造型的溝通與建議<\/span><\/span><\/span><\/span><\/strong><\/em>\n\t\t<\/div>\n\t\t<div><span style=\"font-family: 新細明體;\"><span style=\"background-color: rgb(255, 255, 255);\"><span style=\"color: rgb(0, 0, 255);\"><span style=\"font-size: 16px;\"><br><\/span><\/span><\/span><\/span>\n\t\t<\/div>\n\t\t<div><em><strong><span style=\"font-family: 新細明體;\"><span style=\"background-color: rgb(255, 255, 255);\"><span style=\"color: rgb(0, 0, 255);\"><span style=\"font-size: 16px;\">‧針對不同禮服特色提供配件\/項鍊\/耳環\/頭飾\/手飾等整體造型搭配<\/span><\/span><\/span><\/span><\/strong><\/em>\n\t\t<\/div>\n\t\t<div><em><strong><span style=\"font-family: 新細明體;\"><span style=\"background-color: rgb(255, 255, 255);\"><span style=\"color: rgb(0, 0, 255);\"><span style=\"font-size: 16px;\">&nbsp; &nbsp; &nbsp; &nbsp; &nbsp; &nbsp; &nbsp; &nbsp;&nbsp;<\/span><\/span><\/span><\/span><\/strong><\/em>\n\t\t<\/div>\n\t\t<div><em><strong><span style=\"font-family: 新細明體;\"><span style=\"background-color: rgb(255, 255, 255);\"><span style=\"color: rgb(0, 0, 255);\"><span style=\"font-size: 16px;\">‧身體水粉、手部指甲油<\/span><\/span><\/span><\/span><\/strong><\/em>\n\t\t<\/div>\n\t\t<div><em><strong><span style=\"font-family: 新細明體;\"><span style=\"background-color: rgb(255, 255, 255);\"><span style=\"color: rgb(0, 0, 255);\"><span style=\"font-size: 16px;\">&nbsp; &nbsp; &nbsp; &nbsp; &nbsp; &nbsp; &nbsp;&nbsp;<\/span><\/span><\/span><\/span><\/strong><\/em>\n\t\t<\/div>\n\t\t<div><em><strong><span style=\"font-family: 新細明體;\"><span style=\"background-color: rgb(255, 255, 255);\"><span style=\"color: rgb(0, 0, 255);\"><span style=\"font-size: 16px;\">. 協助穿著禮服<\/span><\/span><\/span><\/span><\/strong><\/em>\n\t\t<\/div><span style=\"font-family: 新細明體;\"><span style=\"background-color: rgb(255, 255, 255);\"><span style=\"color: rgb(0, 0, 255);\"><span style=\"font-size: 16px;\">　<\/span><\/span><\/span><\/span>\n\t<\/div>\n<\/ul>","blog-name":"Eunice新娘秘書","blog-id":"5895957","blog-category":"13","date":"2015-11-13","hits":"71"}
{"username":"MollyMolly263","authorid":"5897531","url":"http:\/\/mollymolly263.pixnet.net\/blog\/post\/1136855","title":"工欲善其事 必先利其器","content":"<p>MollyMolly的小小溫馨工作室，麻雀雖小可是五臟俱全✨MollyMolly在客人使用的凝膠產品都是韓國以及日本的棒棒優質品哦！當然Molly也會在自己手上創作所以對於品質注重當然非常重要囉💪🏻放心的交給MollyMollyㄧ起尋覓生活小雀幸吧😘&nbsp;<br><img src=\"https:\/\/pic.pimg.tw\/mollymolly263\/1447513992-2082286639_n.jpg\" alt=\"\">&nbsp;<\/p>","blog-name":"MollyMolly manicure","blog-id":"5897531","blog-category":"0","date":"2015-11-14","hits":"9"}
{"username":"jiecian","authorid":"5895791","url":"http:\/\/jiecian.pixnet.net\/blog\/post\/2647283-%e3%80%90%e5%82%91%e9%a8%ab%e5%9c%8b%e9%9a%9b%e3%80%91%e4%b8%89%e9%ba%97%e9%b7%97-%e6%ad%a3%e7%89%88%e6%8e%88%e6%ac%8a-hello-kitty-melody","title":"【傑騫國際】三麗鷗 正版授權 Hello Kitty Melody美樂蒂 For HTC One E9+","content":"<p style=\"text-align: center;\"><img title=\"0746.jpg\" src=\"https:\/\/pic.pimg.tw\/jiecian\/1447730571-795312217_n.jpg?v=1447730601\" alt=\"0746.jpg\" border=\"0\" \/><\/p>\r\n<p style=\"text-align: center;\">&nbsp;<\/p>\r\n<p style=\"text-align: center;\"><img title=\"0748.jpg\" src=\"https:\/\/pic.pimg.tw\/jiecian\/1447730571-3725545060_n.jpg?v=1447730601\" alt=\"0748.jpg\" border=\"0\" \/><\/p>\r\n<p style=\"text-align: center;\">&nbsp;<\/p>\r\n<p style=\"text-align: center;\"><img title=\"0749.jpg\" src=\"https:\/\/pic.pimg.tw\/jiecian\/1447730572-2696350352_n.jpg?v=1447730601\" alt=\"0749.jpg\" border=\"0\" \/><\/p>\r\n<p style=\"text-align: center;\">&nbsp;<\/p>\r\n<p style=\"text-align: center;\"><img title=\"0750.jpg\" src=\"https:\/\/pic.pimg.tw\/jiecian\/1447730573-2125173326_n.jpg?v=1447730601\" alt=\"0750.jpg\" border=\"0\" \/><\/p>\r\n<p style=\"text-align: center;\">&nbsp;<\/p>\r\n<p style=\"text-align: center;\"><img title=\"0751.jpg\" src=\"https:\/\/pic.pimg.tw\/jiecian\/1447730574-843661122_n.jpg?v=1447730601\" alt=\"0751.jpg\" border=\"0\" \/><\/p>\r\n<p style=\"text-align: center;\">&nbsp;<\/p>\r\n<p style=\"text-align: center;\"><img title=\"0752.jpg\" src=\"https:\/\/pic.pimg.tw\/jiecian\/1447730575-3392073073_n.jpg?v=1447730601\" alt=\"0752.jpg\" border=\"0\" \/><\/p>\r\n<p style=\"text-align: center;\">&nbsp;<\/p>\r\n<p style=\"text-align: center;\"><img title=\"0753.jpg\" src=\"https:\/\/pic.pimg.tw\/jiecian\/1447730576-4241738906_n.jpg?v=1447730601\" alt=\"0753.jpg\" border=\"0\" \/><\/p>\r\n<p style=\"text-align: center;\">&nbsp;<\/p>\r\n<p style=\"text-align: center;\"><img title=\"0754.jpg\" src=\"https:\/\/pic.pimg.tw\/jiecian\/1447730576-596065545_n.jpg?v=1447730601\" alt=\"0754.jpg\" border=\"0\" \/><\/p>\r\n<p style=\"text-align: center;\">&nbsp;<\/p>\r\n<p style=\"text-align: center;\"><img title=\"0755.jpg\" src=\"https:\/\/pic.pimg.tw\/jiecian\/1447730577-286734221_n.jpg?v=1447730601\" alt=\"0755.jpg\" border=\"0\" \/><\/p>\r\n<p style=\"text-align: center;\">&nbsp;<\/p>\r\n<p style=\"text-align: center;\"><img title=\"0756.jpg\" src=\"https:\/\/pic.pimg.tw\/jiecian\/1447730578-3650640117_n.jpg?v=1447730601\" alt=\"0756.jpg\" border=\"0\" \/><\/p>\r\n<p style=\"text-align: center;\">&nbsp;<\/p>\r\n<p style=\"text-align: center;\"><img title=\"0757.jpg\" src=\"https:\/\/pic.pimg.tw\/jiecian\/1447730579-190913998_n.jpg?v=1447730601\" alt=\"0757.jpg\" border=\"0\" \/><\/p>\r\n<p style=\"text-align: center;\">&nbsp;<\/p>\r\n<p style=\"text-align: center;\"><img title=\"0758.jpg\" src=\"https:\/\/pic.pimg.tw\/jiecian\/1447730580-1951788958_n.jpg?v=1447730601\" alt=\"0758.jpg\" border=\"0\" \/><\/p>\r\n<p style=\"text-align: center;\">&nbsp;<\/p>\r\n<p style=\"text-align: center;\"><img title=\"0759.jpg\" src=\"https:\/\/pic.pimg.tw\/jiecian\/1447730581-2117693442_n.jpg?v=1447730601\" alt=\"0759.jpg\" border=\"0\" \/><\/p>\r\n<p style=\"text-align: center;\">&nbsp;<\/p>\r\n<p style=\"text-align: center;\"><img title=\"0760.jpg\" src=\"https:\/\/pic.pimg.tw\/jiecian\/1447730581-3806276010_n.jpg?v=1447730601\" alt=\"0760.jpg\" border=\"0\" \/><\/p>\r\n<p style=\"text-align: center;\">&nbsp;<\/p>\r\n<p style=\"text-align: center;\"><img title=\"0761.jpg\" src=\"https:\/\/pic.pimg.tw\/jiecian\/1447730582-2899037458_n.jpg?v=1447730601\" alt=\"0761.jpg\" border=\"0\" \/><\/p>\r\n<p style=\"text-align: center;\">&nbsp;<\/p>\r\n<p style=\"text-align: center;\"><img title=\"0763.jpg\" src=\"https:\/\/pic.pimg.tw\/jiecian\/1447730583-1196655493_n.jpg?v=1447730601\" alt=\"0763.jpg\" border=\"0\" \/><\/p>\r\n<p style=\"text-align: center;\">&nbsp;<\/p>\r\n<p style=\"text-align: center;\"><img title=\"0766.jpg\" src=\"https:\/\/pic.pimg.tw\/jiecian\/1447730588-4221081054_n.jpg?v=1447730601\" alt=\"0766.jpg\" border=\"0\" \/><\/p>\r\n<p style=\"text-align: center;\">&nbsp;<\/p>\r\n<p style=\"text-align: center;\"><img title=\"0767.jpg\" src=\"https:\/\/pic.pimg.tw\/jiecian\/1447730594-4095263420_n.jpg?v=1447730601\" alt=\"0767.jpg\" border=\"0\" \/> &nbsp;<\/p>\r\n<p style=\"text-align: center;\">&nbsp;<\/p>\r\n<p>&nbsp;<\/p>\r\n<p style=\"text-align: center;\"><span style=\"font-size: 18px;\"><strong><span style=\"color: #0000ff;\">傑騫國際<\/span><span style=\"color: #ff0000;\">★FB粉絲專頁★<\/span><\/strong><\/span><\/p>\r\n<p style=\"text-align: center;\"><span style=\"font-size: 18px;\"><strong>&nbsp;<\/strong><\/span><\/p>\r\n<p style=\"text-align: center;\"><span style=\"font-size: 18px;\"><strong>&nbsp;<a href=\"https:\/\/www.facebook.com\/JieCianDesign\">https:\/\/www.facebook.com\/JieCianDesign<\/a><\/strong><\/span><\/p>\r\n<p style=\"text-align: center;\"><span style=\"font-size: 18px;\"><strong>&nbsp;<\/strong><\/span><\/p>\r\n<p style=\"text-align: center;\"><span style=\"font-size: 18px;\"><span style=\"color: #ff0000;\"><strong>想要掌握<span style=\"color: #0000ff;\">\"傑騫國際\"<\/span>的近況嗎?<\/strong><\/span><\/span><\/p>\r\n<p style=\"text-align: center;\"><span style=\"font-size: 18px;\"><span style=\"color: #ff0000;\"><strong>&nbsp;<\/strong><\/span><\/span><\/p>\r\n<p style=\"text-align: center;\"><span style=\"font-size: 18px;\"><span style=\"color: #ff0000;\"><strong>請至FB粉絲專頁按讚，可以掌握最新資訊唷!<\/strong><\/span><\/span><\/p>\r\n<p style=\"text-align: center;\"><span style=\"font-size: 18px;\">&nbsp;<\/span><\/p>\r\n<p style=\"text-align: center;\"><span style=\"font-size: 18px;\">&nbsp;<\/span><\/p>\r\n<p style=\"text-align: center;\"><span class=\"redactor-invisible-space\">&nbsp;<\/span><\/p>","blog-name":"傑騫國際有限公司","blog-id":"5895791","blog-category":"15","date":"2015-11-17","hits":"6"}
{"username":"yuchi0907","authorid":"5902516","url":"http:\/\/yuchi0907.pixnet.net\/blog\/post\/2651030-velours-hair%e6%a1%83%e5%9c%92%e5%ba%97-%e5%ba%97%e9%95%b7eason-%e6%a1%83%e5%9c%92%e7%87%99%e9%ab%ae-%e6%9f%93%e9%ab%ae%e5%88%86%e4%ba%ab","title":"velours hair桃園店 店長Eason 桃園燙髮 染髮分享","content":"<p><span style=\"font-size: 16px;\">我住台北在大學時代裏 ,我就已經給<strong>EASON<\/strong> 用頭髮 到現在已經7~8年囉!&nbsp;每次來用頭髮我都帶著期待的心,EASON 每次給我用的髮型 我都很滿意<\/span>\n<\/p>\n<p><span style=\"font-size: 16px;\">這次來到<strong>EASON<\/strong>新開的店 &nbsp;<strong>桃園VELOURS HAIR &nbsp;SAILON<\/strong> &nbsp;燙髮跟染髮......<\/span>\n<\/p>\n<p><img src=\"https:\/\/pic.pimg.tw\/yuchi0907\/1447738183-321307811_n.jpg?v=1447738215\" alt=\"IMG_0278.JPG\">&nbsp;&nbsp;\n<\/p>\n<p><span style=\"font-size: 16px;\"><strong>EASON<\/strong> 的店變得很大 有1~2~3 樓 &nbsp;很漂亮 &nbsp;他們的接待服務讓我感覺很溫暖 茶水還有面紙跟棉花棒<\/span><br>\n<\/p>\n<p><span style=\"font-size: 16px;\"><img src=\"https:\/\/pic.pimg.tw\/yuchi0907\/1447740722-3442637771_n.jpg?v=1447740733\" alt=\"IMG_0463.JPG\">&nbsp;<br><\/span>\n<\/p>\n<p><span style=\"font-size: 16px;\"><br><\/span>\n<\/p>\n<p><span style=\"font-size: 16px;\">這次跟<strong>EASON<\/strong> 討論要怎麼用我的頭髮 &nbsp;我跟他說我的需求 我想留長但不想剪長度 &nbsp;顏色 我想換色 &nbsp;燙髮想燙髮尾就好&nbsp;<br>\n\t<\/span>\n<\/p>\n<p><span style=\"font-size: 16px;\"><strong>EASON<\/strong> 很專業的建議我 可以燙 最新的 日本醫學髮妝燙 我髮尾毛燥都可以用護理的方式做燙髮 &nbsp;藥水是用無鹼的藥劑塗佈<\/span>\n<\/p>\n<p><span style=\"font-size: 16px;\">在染髮上<strong>EASON<\/strong> 建議我可以換 麻霧栗銀色 是今年 2015 年最新流行的髮色 我很開心 也很放心地交給<\/span><strong><span style=\"font-size: 16px;\">EASON 店長設計師.....<\/span><\/strong>\n<\/p>\n<p><strong><span style=\"font-size: 16px;\"><\/span><\/strong><strong><span style=\"font-size: 16px;\"><strong><span style=\"font-size: 16px;\"><img src=\"https:\/\/pic.pimg.tw\/yuchi0907\/1447738190-657107694_m.jpg?v=1447740733\" alt=\"IMG_0526.JPG\">&nbsp;<\/span><\/strong><\/span><\/strong>\n<\/p>\n<p><span style=\"font-size: 16px;\">燙完 哇 真的 讓我的髮尾好好整理喔 ~ 而且觸感 好鬆軟 &gt;&gt;&gt;&gt;&gt;&gt;&gt;<\/span>\n<\/p>\n<p><span style=\"font-size: 16px;\"><span style=\"font-size: 16px;\">顏色也好自然好好看 &nbsp;我好喜歡 &nbsp;&nbsp;.....<img src=\"\/\/s.pixfs.net\/f.pixnet.net\/images\/emotions\/017.gif\"><span class=\"redactor-invisible-space\"><\/span><\/span><\/span>\n<\/p>\n<p><span style=\"font-size: 16px;\"><span style=\"font-size: 16px;\"><span class=\"redactor-invisible-space\"><img src=\"https:\/\/pic.pimg.tw\/yuchi0907\/1447738201-174064192_m.jpg?v=1447740733\" alt=\"IMG_0527.JPG\">&nbsp;<span class=\"redactor-invisible-space\"><br><\/span><\/span><\/span><\/span>\n<\/p>\n<p><span style=\"font-size: 16px;\"><span style=\"font-size: 16px;\"><span class=\"redactor-invisible-space\"><span class=\"redactor-invisible-space\"><img src=\"https:\/\/pic.pimg.tw\/yuchi0907\/1447738187-1945729148_q.jpg?v=1447740733\" alt=\"IMG_0525.JPG\">&nbsp;<span class=\"redactor-invisible-space\"><br><\/span><\/span><\/span><\/span><\/span>\n<\/p>\n<p><span style=\"font-size: 16px;\"><span style=\"font-size: 16px;\"><span class=\"redactor-invisible-space\"><span class=\"redactor-invisible-space\"><strong>EASON&nbsp;<\/strong> 建議我產品只要用&nbsp;<strong>(摩洛哥優油)&nbsp;<\/strong>說我只要往內吹乾 手捲繞吹 就會呈現 像電棒的 浪漫大捲^^<img src=\"https:\/\/s.pixfs.net\/f.pixnet.net\/images\/emotions\/fox_12.gif\"><br><\/span><\/span><\/span><\/span>\n<\/p>\n<p><span style=\"font-size: 16px;\"><span style=\"font-size: 16px;\"><span class=\"redactor-invisible-space\"><span class=\"redactor-invisible-space\"><br><\/span><\/span><\/span><\/span>\n<\/p>\n<p><img src=\"https:\/\/pic.pimg.tw\/yuchi0907\/1447742827-1393555335_q.jpg?v=1447742840\" alt=\"p021163186334-item-6778xf2x0600x0600-m.jpg\">&nbsp;\n<\/p>\n<p><img src=\"https:\/\/pic.pimg.tw\/yuchi0907\/1447742832-1828522359_q.jpg?v=1447742840\" alt=\"照片_438.jpg\">&nbsp;\n<\/p>\n<p><span style=\"font-size: 16px;\">大推<strong>EASON<\/strong> 店長 服務好 又細心...<img src=\"https:\/\/pic.pimg.tw\/yuchi0907\/1447738202-3201544626_q.jpg?v=1447740733\" alt=\"IMG_0532.JPG\">&nbsp;<\/span>\n<\/p>\n<p><span style=\"font-size: 16px;\"><span style=\"color: rgb(0, 0, 255);\"><strong><span style=\"background-color: rgb(255, 255, 255);\">FB<\/span><\/strong> <\/span>搜尋 <strong>伊神<\/strong> 就找的到他囉!<\/span>\n<\/p>\n<p><span style=\"font-size: 16px;\"><img src=\"https:\/\/pic.pimg.tw\/yuchi0907\/1447738102-453792616_q.jpg?v=1447742840\" alt=\"IMG_0008.JPG\">&nbsp;<br><\/span>\n<\/p>\n<p>&nbsp;VELOURS HAIR SALON\n<\/p>\n<p>地址: 桃園市桃園區 中山路883號\n<\/p>\n<p>電話:03-3786696 &nbsp;0916959969\n<\/p>\n<p><img src=\"https:\/\/pic.pimg.tw\/yuchi0907\/1447744045-3317346527_q.jpg?v=1447744052\" alt=\"IMG_4127[1].JPG\">&nbsp;<br>\n<\/p>\n<p>這是LINE 的QR 可以加EASON 的LINE 詢問喔!<img src=\"\/\/s.pixfs.net\/f.pixnet.net\/images\/emotions\/fox_10.gif\"><span class=\"redactor-invisible-space\"><\/span>\n<\/p>\n<p><br>\n<\/p>","blog-name":"yuchi隨意日記","blog-id":"5902516","blog-category":"28","date":"2015-11-17","hits":"150"}
{"username":"jiecian","authorid":"5895791","url":"http:\/\/jiecian.pixnet.net\/blog\/post\/2656886-%e3%80%90%e5%82%91%e9%a8%ab%e5%9c%8b%e9%9a%9b%e3%80%91%e5%82%91%e9%a8%ab%e5%9c%8b%e9%9a%9b%e6%9c%89%e9%99%90%e5%85%ac%e5%8f%b8jie-cian-internati","title":"【傑騫國際】傑騫國際有限公司JIE CIAN INTERNATIONAL CO.,LTD","content":"<p style=\"text-align: center;\"><img style=\"display: block; margin-left: auto; margin-right: auto;\" title=\"jiecian\" src=\"https:\/\/pic.pimg.tw\/jiecian\/1447740679-3268735410_n.jpg?v=1447740848\" alt=\"jiecian\" border=\"0\" \/><\/p>\r\n<p style=\"text-align: center;\">&nbsp;<\/p>\r\n<p style=\"text-align: center;\">&nbsp;<strong style=\"text-align: center;\"><span style=\"color: #ffffff; font-size: 24pt; background-color: #000000;\">公司介紹<\/span><\/strong><\/p>\r\n<p style=\"text-align: center;\"><span style=\"font-size: 12pt;\"><span style=\"color: #0000ff;\"><strong>傑騫國際<\/strong><\/span><span style=\"color: #b8860b;\">於2009年成立，其主要業務為品牌角色與產品的結合，<\/span><\/span><\/p>\r\n<p style=\"text-align: center;\"><span style=\"font-size: 12pt;\"><span style=\"color: #b8860b;\">使企業與機構其產品擁有獨特的識別，並在競爭者中形成差異化來建立及相對應的營銷方案，<\/span><\/span><\/p>\r\n<p style=\"text-align: center;\"><span style=\"font-size: 12pt; color: #b8860b;\">我們的團隊曾參加打造多個國際娛樂品牌，製造了多個全球的熱潮並為產業帶來無限商機，<\/span><\/p>\r\n<p style=\"text-align: center;\"><span style=\"font-size: 12pt; color: #b8860b;\"> 利用我們的知識和經驗，來吸引及跨大目標消費群，<\/span><\/p>\r\n<p style=\"text-align: center;\"><span style=\"font-size: 12pt; color: #b8860b;\"> 令品牌及產品的受關注度及使用者黏貼度大大提高，<\/span><\/p>\r\n<p style=\"text-align: center;\"><span style=\"font-size: 12pt; color: #b8860b;\"> 而且能為品牌角色提供相關精品設計及生產監控，以及角色授權(經銷)顧問服務。<\/span><\/p>\r\n<p style=\"text-align: left;\">&nbsp;<\/p>\r\n<p style=\"text-align: center;\"><img title=\"小小兵\" src=\"https:\/\/pic.pimg.tw\/jiecian\/1447744597-855199528.jpg?v=1447744599\" alt=\"小小兵\" border=\"0\" \/>&nbsp; &nbsp; &nbsp;&nbsp;<img title=\"加藤真治\" src=\"https:\/\/pic.pimg.tw\/jiecian\/1447744597-2488171413.jpg\" alt=\"加藤真治\" border=\"0\" \/> &nbsp;<\/p>\r\n<p style=\"text-align: center;\">&nbsp;<\/p>\r\n<p style=\"text-align: center;\"><strong style=\"text-align: center;\"><span style=\"color: #ffffff; font-size: 24pt; background-color: #000000;\">品牌系列<\/span><\/strong><span style=\"text-align: center;\">&nbsp;<\/span>&nbsp;<\/p>\r\n<p style=\"text-align: center;\"><span style=\"font-size: 12pt;\"><span style=\"color: #0000ff;\"><strong> 傑騫國際<\/strong><\/span><span style=\"color: #b8860b;\">擁有\"神偷奶爸\"Minions小小兵、Shinzi Katoh加藤真治、<\/span><\/span><\/p>\r\n<p style=\"text-align: center;\"><span style=\"font-size: 12pt; color: #b8860b;\">Rilakkuma拉拉熊、Gudetama蛋黃哥、原子小金剛(阿童木)<span style=\"color: #b8860b; font-size: 16px; text-align: center;\">、<\/span><\/span><\/p>\r\n<p style=\"text-align: center;\"><span style=\"font-size: 12pt; color: #b8860b;\">The Bears'school小熊學校<span style=\"color: #b8860b; font-size: 16px; text-align: center;\">、Kanahei卡娜赫拉<\/span><\/span><span style=\"color: #b8860b; font-size: 12pt;\">等日本及海外知名品牌眾多授權(經銷)。<\/span><\/p>\r\n<p style=\"text-align: center;\">&nbsp;<\/p>\r\n<p style=\"text-align: center;\"><img title=\"小熊學校\" src=\"https:\/\/pic.pimg.tw\/jiecian\/1447747211-3829318044_n.jpg?v=1447747212\" alt=\"小熊學校\" border=\"0\" \/> &nbsp;<\/p>\r\n<p style=\"text-align: center;\">&nbsp;<\/p>\r\n<p style=\"text-align: center;\"><img title=\"卡娜赫拉\" src=\"https:\/\/pic.pimg.tw\/jiecian\/1447747458-2275701233_n.png?v=1447747460\" alt=\"卡娜赫拉\" border=\"0\" \/> &nbsp;<\/p>\r\n<p style=\"text-align: center;\">&nbsp;<\/p>\r\n<p style=\"text-align: center;\"><strong style=\"text-align: center;\"><span style=\"color: #ffffff; font-size: 24pt; background-color: #000000;\">品牌合作<\/span><\/strong>&nbsp;<\/p>\r\n<p style=\"text-align: center;\"><span style=\"font-size: 12pt;\"><strong><span style=\"color: #0000ff;\">傑騫國際<\/span><\/strong><span style=\"color: #b8860b;\">目前代理及經銷之商品，已於國內各大3C連鎖通路上架，<\/span><\/span><\/p>\r\n<p style=\"text-align: center;\"><span style=\"font-size: 12pt; color: #b8860b;\">如中華電信、遠傳電信<span style=\"text-align: center;\">、台灣大哥大<span style=\"text-align: center;\">、<\/span><\/span><\/span><\/p>\r\n<p style=\"text-align: center;\"><span style=\"text-align: center; font-size: 12pt; color: #b8860b;\"><span style=\"text-align: center;\">台灣之星<span style=\"text-align: center;\">、威寶電信和<span style=\"text-align: center;\">家樂福量販中心等皆可看到本公司商品。<\/span><\/span><\/span><\/span><\/p>\r\n<p style=\"text-align: center;\">&nbsp;<\/p>\r\n<p style=\"text-align: center;\">&nbsp;<\/p>\r\n<p style=\"text-align: center;\"><span style=\"text-align: center; font-size: 12pt; color: #b8860b;\"><span style=\"text-align: center;\"><span style=\"text-align: center;\"><span style=\"text-align: center;\"><img title=\"3c業者\" src=\"https:\/\/pic.pimg.tw\/jiecian\/1447747712-2236334546.png?v=1447747713\" alt=\"3c業者\" border=\"0\" \/> &nbsp;<\/span><\/span><\/span><\/span>&nbsp;<\/p>\r\n<p style=\"text-align: center;\">&nbsp;<\/p>\r\n<p style=\"text-align: center;\">&nbsp;<\/p>\r\n<p style=\"text-align: center;\"><strong><span style=\"color: #ffffff; font-size: 24pt; background-color: #000000;\">公司資訊<\/span><\/strong><\/p>\r\n<p style=\"text-align: center;\"><span style=\"font-size: 12pt; color: #b8860b;\"><strong><span style=\"color: #0000ff;\"> 傑騫國際有限公司<\/span><\/strong> JIE CIAN INTERNATIONAL CO.,LTD <\/span><\/p>\r\n<p style=\"text-align: center;\"><span style=\"font-size: 12pt; color: #b8860b;\">103台北市大同區重慶北路一段34號2樓 <\/span><\/p>\r\n<p style=\"text-align: center;\"><span style=\"font-size: 12pt; color: #b8860b;\">2F.,NO.34, Sec, 1,Chongging N Rd., Datong Dist Taipei City 103, Taiwan(R.O.C) <\/span><\/p>\r\n<p style=\"text-align: center;\"><span style=\"font-size: 12pt; color: #b8860b;\">TEL:02-25527831 <\/span><\/p>\r\n<p style=\"text-align: center;\"><span style=\"font-size: 12pt; color: #b8860b;\">E-MAIL:ricky@jie-cian.com<\/span><\/p>\r\n<p style=\"text-align: center;\">&nbsp;<\/p>\r\n<p style=\"text-align: center;\"><span style=\"font-size: 12pt; color: #b8860b;\"><strong style=\"text-align: center;\"><span style=\"color: #ffffff; font-size: 24pt; background-color: #000000;\">FB粉絲專頁<\/span><\/strong><\/span><\/p>\r\n<p style=\"text-align: center;\">&nbsp;&nbsp;<\/p>\r\n<p style=\"text-align: center;\"><span style=\"font-size: 18px;\"><strong><span style=\"color: #0000ff;\">傑騫國際<\/span><span style=\"color: #ff0000;\">★FB粉絲專頁★<\/span><\/strong><\/span><\/p>\r\n<p style=\"text-align: center;\"><span style=\"font-size: 18px;\"><strong>&nbsp;<\/strong><\/span><\/p>\r\n<p style=\"text-align: center;\"><span style=\"font-size: 18px;\"><strong>&nbsp;<a href=\"https:\/\/www.facebook.com\/JieCianDesign\">https:\/\/www.facebook.com\/JieCianDesign<\/a><\/strong><\/span><\/p>\r\n<p style=\"text-align: center;\"><span style=\"font-size: 18px;\"><strong>&nbsp;<\/strong><\/span><\/p>\r\n<p style=\"text-align: center;\"><span style=\"font-size: 18px;\"><span style=\"color: #ff0000;\"><strong>想要掌握<span style=\"color: #0000ff;\">\"傑騫國際\"<\/span>的近況嗎?<\/strong><\/span><\/span><\/p>\r\n<p style=\"text-align: center;\"><span style=\"font-size: 18px;\"><span style=\"color: #ff0000;\"><strong>&nbsp;<\/strong><\/span><\/span><\/p>\r\n<p style=\"text-align: center;\"><span style=\"font-size: 18px;\"><span style=\"color: #ff0000;\"><strong>請至FB粉絲專頁按讚，可以掌握最新資訊唷!<\/strong><\/span><\/span><\/p>\r\n<p style=\"text-align: center;\"><span style=\"font-size: 18px;\">&nbsp;<\/span><\/p>\r\n<p style=\"text-align: center;\"><span style=\"font-size: 18px;\">&nbsp;<\/span><\/p>\r\n<p style=\"text-align: center;\">&nbsp;<\/p>\r\n<p style=\"text-align: center;\">&nbsp;<\/p>\r\n<p style=\"text-align: center;\">&nbsp;<\/p>\r\n<p style=\"text-align: center;\"><span class=\"redactor-invisible-space\">&nbsp;<\/span><\/p>","blog-name":"傑騫國際有限公司","blog-id":"5895791","blog-category":"15","date":"2015-11-17","hits":"74"}
